bamboo_duck/__init__.py
bamboo_duck/main.py
bamboo_duck/my_function.py
bamboo_duck/parsewith.py
bamboo_duck-1.1.dist-info/LICENSE
bamboo_duck-1.1.dist-info/METADATA
bamboo_duck-1.1.dist-info/WHEEL
bamboo_duck-1.1.dist-info/entry_points.txt
bamboo_duck-1.1.dist-info/top_level.txt
bamboo_duck-1.1.dist-info/RECORD
